qbertconfig/Kubeconfig.py
qbertconfig/QbertClient.py
qbertconfig/__init__.py
qbertconfig/cli/__init__.py
qbertconfig/cli/dispatcher.py
qbertconfig/cli/main.py
qbertconfig-0.1.2.dist-info/METADATA
qbertconfig-0.1.2.dist-info/RECORD
qbertconfig-0.1.2.dist-info/WHEEL
qbertconfig-0.1.2.dist-info/entry_points.txt
qbertconfig-0.1.2.dist-info/top_level.txt
