Metadata-Version: 2.1
Name: qbertconfig
Version: 0.1.2
Summary: Fetches kubeconfigs from qbert API
Home-page: https://github.com/platform9-incubator/qbertconfig
Author: Graham Rounds
Author-email: graham@platform9.com
License: Apache License 2.0
Keywords: Kubeconfig Qbert Platform9 PMK
Platform: UNKNOWN
Classifier: Environment :: OpenStack
Classifier: Intended Audience :: System Administrators
Classifier: Operating System :: POSIX :: Linux
Classifier: Programming Language :: Python :: 2
Classifier: Programming Language :: Python :: 2.7
Requires-Dist: keystoneauth1
Requires-Dist: os-client-config (==1.29.0)
